obrpy/PathSelector.py
obrpy/__init__.py
obrpy/checkouts.py
obrpy/clear.py
obrpy/fuego.py
obrpy/funciones.py
obrpy/gui.py
obrpy/load.py
obrpy/obr.py
obrpy/obrsdk.py
obrpy/save.py
obrpy/settings.py
obrpy/take_a_look.py
obrpy/to_export.py
obrpy/to_import.py
obrpy/update.py
obrpy/ANALYSIS/global_analysis.py
obrpy/ANALYSIS/local_analysis.py
obrpy/SIGNAL/__init__.py
obrpy/SIGNAL/cross_spectrum.py
obrpy/SIGNAL/spectral_shift.py
obrpy/UTILS/read_OBR.py
obrpy/UTILS/utils.py
obrpy/ZERO_LAYERS/psss.py
obrpy/obrsdk/CommandProcessor.dll
obrpy/obrsdk/CyUSBComm.dll
obrpy/obrsdk/KL2DLL32.DLL
obrpy/obrsdk/LtCore.dll
obrpy/obrsdk/LtMath.dll
obrpy/obrsdk/Phoenix.dll
obrpy/obrsdk/RemoteInterface.dll
obrpy/obrsdk/boost_date_time-mt.dll
obrpy/obrsdk/boost_filesystem-mt.dll
obrpy/obrsdk/boost_system-mt.dll
obrpy/obrsdk/boost_thread-mt.dll
obrpy/obrsdk/copyfeatures_txt.bat
obrpy/obrsdk/copyfeatures_txt_xp.bat
obrpy/obrsdk/features.txt
obrpy/obrsdk/libiomp5md.dll
obrpy/obrsdk/obr.exe
obrpy/obrsdk/ova32.dll
obrpy/obrsdk/ova32.lib
obrpy/obrsdk/ovaGUI.dll
obrpy/obrsdk/vcredist_x86.exe
obrpy/submodule/__init__.py
obrpy/submodule/function.py
obrpy-0.1.8.dist-info/METADATA
obrpy-0.1.8.dist-info/WHEEL
obrpy-0.1.8.dist-info/top_level.txt
obrpy-0.1.8.dist-info/RECORD
