Metadata-Version: 2.1
Name: obrpy
Version: 0.1.8
Summary: This library is aimed for using Luna's OBR-4600 with Python.
Home-page: https://github.com/temisAP
Author: Andres Pedraza Rodriguez
Author-email: a.pedraza@upm.es
License: MIT
Requires-Dist: bleach
Requires-Dist: certifi
Requires-Dist: charset-normalizer
Requires-Dist: contourpy
Requires-Dist: cycler
Requires-Dist: Cython
Requires-Dist: docutils
Requires-Dist: et-xmlfile
Requires-Dist: fastrlock
Requires-Dist: fonttools
Requires-Dist: idna
Requires-Dist: importlib-metadata
Requires-Dist: jaraco.classes
Requires-Dist: keyring
Requires-Dist: kiwisolver
Requires-Dist: markdown-it-py
Requires-Dist: matplotlib
Requires-Dist: mdurl
Requires-Dist: more-itertools
Requires-Dist: networkx
Requires-Dist: nibabel
Requires-Dist: nitime
Requires-Dist: numpy
Requires-Dist: openpyxl
Requires-Dist: packaging
Requires-Dist: pandas
Requires-Dist: Pillow
Requires-Dist: pkginfo
Requires-Dist: psutil
Requires-Dist: Pygments
Requires-Dist: pyparsing
Requires-Dist: python-dateutil
Requires-Dist: pytz
Requires-Dist: pywin32-ctypes
Requires-Dist: readme-renderer
Requires-Dist: requests
Requires-Dist: requests-toolbelt
Requires-Dist: rfc3986
Requires-Dist: rich
Requires-Dist: scipy
Requires-Dist: six
Requires-Dist: twine
Requires-Dist: urllib3
Requires-Dist: webencodings
Requires-Dist: XlsxWriter
Requires-Dist: zipp
